psphere/__init__.py
psphere/client.py
psphere/config.py
psphere/errors.py
psphere/managedobjects.py
psphere/scripting.py
psphere/soap.py
psphere/template.py
psphere/wsdl/core-types.xsd
psphere/wsdl/query-messagetypes.xsd
psphere/wsdl/query-types.xsd
psphere/wsdl/vim-messagetypes.xsd
psphere/wsdl/vim-types.xsd
psphere/wsdl/vim.wsdl
psphere/wsdl/vimService.wsdl
psphere2-0.0.0.dist-info/METADATA
psphere2-0.0.0.dist-info/WHEEL
psphere2-0.0.0.dist-info/top_level.txt
psphere2-0.0.0.dist-info/RECORD
