Metadata-Version: 2.1
Name: psphere2
Version: 0.0.0
Summary: vSphere SDK for Python
Home-page: https://github.com/graingert/psphere
Author: Jonathan Kinred
Author-email: jonathan.kinred@gmail.com
Maintainer: Thomas Grainger
Maintainer-email: psphere@graingert.co.uk
License: UNKNOWN
Keywords: vsphere,vmware
Platform: UNKNOWN
Classifier: Development Status :: 4 - Beta
Classifier: License :: OSI Approved :: MIT License
Requires-Dist: suds-jurko
Requires-Dist: PyYAML
